{
  "trial_id": "expl_16_ctr0_8ep",
  "status": "completed",
  "hypothesis": "E-16: Center weight 0.0 (ablated). Tests whether center loss is necessary for stability. If model collapses to degenerate predictions, confirms center loss is essential. If it trains normally, center loss may not be needed. 8ep probe, no warmup.",
  "backbone": "mobilenet_v3_small",
  "input_size": 224,
  "temporal_T_train": 5,
  "head": "current_direct_bbox",
  "lr": 0.001,
  "epochs": 8,
  "batch_size": 16,
  "train_seed": 42,
  "total_params": 1411684,
  "best_val_miou": 0.2604,
  "best_val_recall_at_0_5": 0.154,
  "final_val_miou_fp32": 0.2475,
  "final_val_recall_at_0_5": 0.1335,
  "final_val_recall_at_0_3": 0.3581,
  "global_area_ratio": 1.0845,
  "mean_sample_area_ratio": 8.8932,
  "empty_pred_rate": 0.0,
  "miou_std_last_3_epochs": 0.0008,
  "gpu_mem_gib": 0.19,
  "inference_fps": 85.7,
  "total_train_time_s": 2351.0,
  "num_workers": 2,
  "no_commit": true,
  "no_push": true,
  "finished_at": "2026-05-10T02:46:12.420837"
}